LICENSE
README.rst
pyproject.toml
src/csvinfo/__init__.py
src/csvinfo/__main__.py
src/csvinfo.egg-info/PKG-INFO
src/csvinfo.egg-info/SOURCES.txt
src/csvinfo.egg-info/dependency_links.txt
src/csvinfo.egg-info/entry_points.txt
src/csvinfo.egg-info/top_level.txt