Metadata-Version: 2.4
Name: csvinfo
Version: 0.0.1
Summary: csv and ssv mixed file parsing, and statistics tabulation
Author-email: Jacob Striebel <author@example.com>
License-Expression: MIT
Project-URL: Homepage, https://github.com/striebel/csvinfo
License-File: LICENSE
Dynamic: license-file
